<?xml version="1.0" encoding="utf-8"?>
<TextureAtlas imagePath="Catdancing1.png">
	<!-- Created with Adobe Animate version 24.0.3.19 -->
	<!-- http://www.adobe.com/products/animate.html -->
	<SubTexture name="dancing-cat-dance_gif0000" x="5" y="5" width="297" height="498"/>
	<SubTexture name="dancing-cat-dance_gif0001" x="5" y="5" width="297" height="498"/>
	<SubTexture name="dancing-cat-dance_gif0002" x="5" y="5" width="297" height="498"/>
	<SubTexture name="dancing-cat-dance_gif0003" x="304" y="5" width="297" height="498"/>
	<SubTexture name="dancing-cat-dance_gif0004" x="304" y="5" width="297" height="498"/>
	<SubTexture name="dancing-cat-dance_gif0005" x="304" y="5" width="297" height="498"/>
	<SubTexture name="dancing-cat-dance_gif0006" x="603" y="5" width="297" height="498"/>
	<SubTexture name="dancing-cat-dance_gif0007" x="603" y="5" width="297" height="498"/>
	<SubTexture name="dancing-cat-dance_gif0008" x="603" y="5" width="297" height="498"/>
	<SubTexture name="dancing-cat-dance_gif0009" x="902" y="5" width="297" height="498"/>
	<SubTexture name="dancing-cat-dance_gif0010" x="902" y="5" width="297" height="498"/>
	<SubTexture name="dancing-cat-dance_gif0011" x="902" y="5" width="297" height="498"/>
	<SubTexture name="dancing-cat-dance_gif0012" x="1201" y="5" width="297" height="498"/>
	<SubTexture name="dancing-cat-dance_gif0013" x="1201" y="5" width="297" height="498"/>
	<SubTexture name="dancing-cat-dance_gif0014" x="1201" y="5" width="297" height="498"/>
	<SubTexture name="dancing-cat-dance_gif0015" x="1500" y="5" width="297" height="498"/>
	<SubTexture name="dancing-cat-dance_gif0016" x="1500" y="5" width="297" height="498"/>
	<SubTexture name="dancing-cat-dance_gif0017" x="1500" y="5" width="297" height="498"/>
	<SubTexture name="dancing-cat-dance_gif0018" x="1799" y="5" width="297" height="498"/>
	<SubTexture name="dancing-cat-dance_gif0019" x="1799" y="5" width="297" height="498"/>
	<SubTexture name="dancing-cat-dance_gif0020" x="1799" y="5" width="297" height="498"/>
	<SubTexture name="dancing-cat-dance_gif0021" x="2098" y="5" width="297" height="498"/>
	<SubTexture name="dancing-cat-dance_gif0022" x="2098" y="5" width="297" height="498"/>
	<SubTexture name="dancing-cat-dance_gif0023" x="2098" y="5" width="297" height="498"/>
	<SubTexture name="dancing-cat-dance_gif0024" x="2397" y="5" width="297" height="498"/>
	<SubTexture name="dancing-cat-dance_gif0025" x="2397" y="5" width="297" height="498"/>
	<SubTexture name="dancing-cat-dance_gif0026" x="2397" y="5" width="297" height="498"/>
	<SubTexture name="dancing-cat-dance_gif0027" x="2696" y="5" width="297" height="498"/>
	<SubTexture name="dancing-cat-dance_gif0028" x="2696" y="5" width="297" height="498"/>
	<SubTexture name="dancing-cat-dance_gif0029" x="2696" y="5" width="297" height="498"/>
	<SubTexture name="dancing-cat-dance_gif0030" x="2995" y="5" width="297" height="498"/>
	<SubTexture name="dancing-cat-dance_gif0031" x="2995" y="5" width="297" height="498"/>
	<SubTexture name="dancing-cat-dance_gif0032" x="2995" y="5" width="297" height="498"/>
	<SubTexture name="dancing-cat-dance_gif0033" x="3294" y="5" width="297" height="498"/>
	<SubTexture name="dancing-cat-dance_gif0034" x="3294" y="5" width="297" height="498"/>
	<SubTexture name="dancing-cat-dance_gif0035" x="3294" y="5" width="297" height="498"/>
	<SubTexture name="dancing-cat-dance_gif0036" x="3593" y="5" width="297" height="498"/>
	<SubTexture name="dancing-cat-dance_gif0037" x="3593" y="5" width="297" height="498"/>
	<SubTexture name="dancing-cat-dance_gif0038" x="3593" y="5" width="297" height="498"/>
	<SubTexture name="dancing-cat-dance_gif0039" x="5" y="505" width="297" height="498"/>
	<SubTexture name="dancing-cat-dance_gif0040" x="5" y="505" width="297" height="498"/>
	<SubTexture name="dancing-cat-dance_gif0041" x="5" y="505" width="297" height="498"/>
	<SubTexture name="dancing-cat-dance_gif0042" x="304" y="505" width="297" height="498"/>
	<SubTexture name="dancing-cat-dance_gif0043" x="304" y="505" width="297" height="498"/>
	<SubTexture name="dancing-cat-dance_gif0044" x="304" y="505" width="297" height="498"/>
	<SubTexture name="dancing-cat-dance_gif0045" x="603" y="505" width="297" height="498"/>
	<SubTexture name="dancing-cat-dance_gif0046" x="603" y="505" width="297" height="498"/>
	<SubTexture name="dancing-cat-dance_gif0047" x="603" y="505" width="297" height="498"/>
	<SubTexture name="dancing-cat-dance_gif0048" x="902" y="505" width="297" height="498"/>
	<SubTexture name="dancing-cat-dance_gif0049" x="902" y="505" width="297" height="498"/>
	<SubTexture name="dancing-cat-dance_gif0050" x="902" y="505" width="297" height="498"/>
	<SubTexture name="dancing-cat-dance_gif0051" x="1201" y="505" width="297" height="498"/>
	<SubTexture name="dancing-cat-dance_gif0052" x="1201" y="505" width="297" height="498"/>
	<SubTexture name="dancing-cat-dance_gif0053" x="1201" y="505" width="297" height="498"/>
	<SubTexture name="dancing-cat-dance_gif0054" x="1500" y="505" width="297" height="498"/>
	<SubTexture name="dancing-cat-dance_gif0055" x="1500" y="505" width="297" height="498"/>
	<SubTexture name="dancing-cat-dance_gif0056" x="1500" y="505" width="297" height="498"/>
	<SubTexture name="dancing-cat-dance_gif0057" x="1799" y="505" width="297" height="498"/>
	<SubTexture name="dancing-cat-dance_gif0058" x="1799" y="505" width="297" height="498"/>
	<SubTexture name="dancing-cat-dance_gif0059" x="1799" y="505" width="297" height="498"/>
	<SubTexture name="dancing-cat-dance_gif0060" x="2098" y="505" width="297" height="498"/>
	<SubTexture name="dancing-cat-dance_gif0061" x="2098" y="505" width="297" height="498"/>
	<SubTexture name="dancing-cat-dance_gif0062" x="2098" y="505" width="297" height="498"/>
	<SubTexture name="dancing-cat-dance_gif0063" x="2397" y="505" width="297" height="498"/>
	<SubTexture name="dancing-cat-dance_gif0064" x="2397" y="505" width="297" height="498"/>
	<SubTexture name="dancing-cat-dance_gif0065" x="2397" y="505" width="297" height="498"/>
	<SubTexture name="dancing-cat-dance_gif0066" x="2696" y="505" width="297" height="498"/>
	<SubTexture name="dancing-cat-dance_gif0067" x="2696" y="505" width="297" height="498"/>
	<SubTexture name="dancing-cat-dance_gif0068" x="2696" y="505" width="297" height="498"/>
	<SubTexture name="dancing-cat-dance_gif0069" x="2995" y="505" width="297" height="498"/>
	<SubTexture name="dancing-cat-dance_gif0070" x="2995" y="505" width="297" height="498"/>
	<SubTexture name="dancing-cat-dance_gif0071" x="2995" y="505" width="297" height="498"/>
	<SubTexture name="dancing-cat-dance_gif0072" x="3294" y="505" width="297" height="498"/>
	<SubTexture name="dancing-cat-dance_gif0073" x="3294" y="505" width="297" height="498"/>
	<SubTexture name="dancing-cat-dance_gif0074" x="3294" y="505" width="297" height="498"/>
	<SubTexture name="dancing-cat-dance_gif0075" x="3593" y="505" width="297" height="498"/>
	<SubTexture name="dancing-cat-dance_gif0076" x="3593" y="505" width="297" height="498"/>
	<SubTexture name="dancing-cat-dance_gif0077" x="3593" y="505" width="297" height="498"/>
	<SubTexture name="dancing-cat-dance_gif0078" x="5" y="1005" width="297" height="498"/>
	<SubTexture name="dancing-cat-dance_gif0079" x="5" y="1005" width="297" height="498"/>
	<SubTexture name="dancing-cat-dance_gif0080" x="5" y="1005" width="297" height="498"/>
	<SubTexture name="dancing-cat-dance_gif0081" x="304" y="1005" width="297" height="498"/>
	<SubTexture name="dancing-cat-dance_gif0082" x="304" y="1005" width="297" height="498"/>
	<SubTexture name="dancing-cat-dance_gif0083" x="304" y="1005" width="297" height="498"/>
	<SubTexture name="dancing-cat-dance_gif0084" x="603" y="1005" width="297" height="498"/>
	<SubTexture name="dancing-cat-dance_gif0085" x="603" y="1005" width="297" height="498"/>
	<SubTexture name="dancing-cat-dance_gif0086" x="603" y="1005" width="297" height="498"/>
	<SubTexture name="dancing-cat-dance_gif0087" x="902" y="1005" width="297" height="498"/>
	<SubTexture name="dancing-cat-dance_gif0088" x="902" y="1005" width="297" height="498"/>
	<SubTexture name="dancing-cat-dance_gif0089" x="902" y="1005" width="297" height="498"/>
	<SubTexture name="dancing-cat-dance_gif0090" x="1201" y="1005" width="297" height="498"/>
	<SubTexture name="dancing-cat-dance_gif0091" x="1201" y="1005" width="297" height="498"/>
	<SubTexture name="dancing-cat-dance_gif0092" x="1201" y="1005" width="297" height="498"/>
	<SubTexture name="dancing-cat-dance_gif0093" x="1500" y="1005" width="297" height="498"/>
	<SubTexture name="dancing-cat-dance_gif0094" x="1500" y="1005" width="297" height="498"/>
	<SubTexture name="dancing-cat-dance_gif0095" x="1500" y="1005" width="297" height="498"/>
	<SubTexture name="dancing-cat-dance_gif0096" x="1799" y="1005" width="297" height="498"/>
	<SubTexture name="dancing-cat-dance_gif0097" x="1799" y="1005" width="297" height="498"/>
	<SubTexture name="dancing-cat-dance_gif0098" x="1799" y="1005" width="297" height="498"/>
	<SubTexture name="dancing-cat-dance_gif0099" x="2098" y="1005" width="297" height="498"/>
	<SubTexture name="dancing-cat-dance_gif0100" x="2098" y="1005" width="297" height="498"/>
	<SubTexture name="dancing-cat-dance_gif0101" x="2098" y="1005" width="297" height="498"/>
	<SubTexture name="dancing-cat-dance_gif0102" x="2397" y="1005" width="297" height="498"/>
	<SubTexture name="dancing-cat-dance_gif0103" x="2397" y="1005" width="297" height="498"/>
	<SubTexture name="dancing-cat-dance_gif0104" x="2397" y="1005" width="297" height="498"/>
	<SubTexture name="dancing-cat-dance_gif0105" x="2696" y="1005" width="297" height="498"/>
	<SubTexture name="dancing-cat-dance_gif0106" x="2696" y="1005" width="297" height="498"/>
	<SubTexture name="dancing-cat-dance_gif0107" x="2696" y="1005" width="297" height="498"/>
	<SubTexture name="dancing-cat-dance_gif0108" x="2995" y="1005" width="297" height="498"/>
	<SubTexture name="dancing-cat-dance_gif0109" x="2995" y="1005" width="297" height="498"/>
	<SubTexture name="dancing-cat-dance_gif0110" x="2995" y="1005" width="297" height="498"/>
	<SubTexture name="dancing-cat-dance_gif0111" x="3294" y="1005" width="297" height="498"/>
	<SubTexture name="dancing-cat-dance_gif0112" x="3294" y="1005" width="297" height="498"/>
	<SubTexture name="dancing-cat-dance_gif0113" x="3294" y="1005" width="297" height="498"/>
	<SubTexture name="dancing-cat-dance_gif0114" x="3593" y="1005" width="297" height="498"/>
	<SubTexture name="dancing-cat-dance_gif0115" x="3593" y="1005" width="297" height="498"/>
	<SubTexture name="dancing-cat-dance_gif0116" x="3593" y="1005" width="297" height="498"/>
	<SubTexture name="dancing-cat-dance_gif0117" x="5" y="1505" width="297" height="498"/>
	<SubTexture name="dancing-cat-dance_gif0118" x="5" y="1505" width="297" height="498"/>
	<SubTexture name="dancing-cat-dance_gif0119" x="5" y="1505" width="297" height="498"/>
	<SubTexture name="dancing-cat-dance_gif0120" x="304" y="1505" width="297" height="498"/>
	<SubTexture name="dancing-cat-dance_gif0121" x="304" y="1505" width="297" height="498"/>
	<SubTexture name="dancing-cat-dance_gif0122" x="304" y="1505" width="297" height="498"/>
	<SubTexture name="dancing-cat-dance_gif0123" x="603" y="1505" width="297" height="498"/>
	<SubTexture name="dancing-cat-dance_gif0124" x="603" y="1505" width="297" height="498"/>
	<SubTexture name="dancing-cat-dance_gif0125" x="603" y="1505" width="297" height="498"/>
	<SubTexture name="dancing-cat-dance_gif0126" x="902" y="1505" width="297" height="498"/>
	<SubTexture name="dancing-cat-dance_gif0127" x="902" y="1505" width="297" height="498"/>
	<SubTexture name="dancing-cat-dance_gif0128" x="902" y="1505" width="297" height="498"/>
	<SubTexture name="dancing-cat-dance_gif0129" x="1201" y="1505" width="297" height="498"/>
	<SubTexture name="dancing-cat-dance_gif0130" x="1201" y="1505" width="297" height="498"/>
	<SubTexture name="dancing-cat-dance_gif0131" x="1201" y="1505" width="297" height="498"/>
	<SubTexture name="dancing-cat-dance_gif0132" x="1500" y="1505" width="297" height="498"/>
	<SubTexture name="dancing-cat-dance_gif0133" x="1500" y="1505" width="297" height="498"/>
	<SubTexture name="dancing-cat-dance_gif0134" x="1500" y="1505" width="297" height="498"/>
	<SubTexture name="dancing-cat-dance_gif0135" x="1799" y="1505" width="297" height="498"/>
	<SubTexture name="dancing-cat-dance_gif0136" x="1799" y="1505" width="297" height="498"/>
	<SubTexture name="dancing-cat-dance_gif0137" x="1799" y="1505" width="297" height="498"/>
	<SubTexture name="dancing-cat-dance_gif0138" x="2098" y="1505" width="297" height="498"/>
	<SubTexture name="dancing-cat-dance_gif0139" x="2098" y="1505" width="297" height="498"/>
	<SubTexture name="dancing-cat-dance_gif0140" x="2098" y="1505" width="297" height="498"/>
	<SubTexture name="dancing-cat-dance_gif0141" x="2397" y="1505" width="297" height="498"/>
	<SubTexture name="dancing-cat-dance_gif0142" x="2397" y="1505" width="297" height="498"/>
	<SubTexture name="dancing-cat-dance_gif0143" x="2397" y="1505" width="297" height="498"/>
	<SubTexture name="dancing-cat-dance_gif0144" x="2696" y="1505" width="297" height="498"/>
	<SubTexture name="dancing-cat-dance_gif0145" x="2696" y="1505" width="297" height="498"/>
	<SubTexture name="dancing-cat-dance_gif0146" x="2696" y="1505" width="297" height="498"/>
	<SubTexture name="dancing-cat-dance_gif0147" x="2995" y="1505" width="297" height="498"/>
	<SubTexture name="dancing-cat-dance_gif0148" x="2995" y="1505" width="297" height="498"/>
	<SubTexture name="dancing-cat-dance_gif0149" x="2995" y="1505" width="297" height="498"/>
	<SubTexture name="dancing-cat-dance_gif0150" x="3294" y="1505" width="297" height="498"/>
	<SubTexture name="dancing-cat-dance_gif0151" x="3294" y="1505" width="297" height="498"/>
	<SubTexture name="dancing-cat-dance_gif0152" x="3294" y="1505" width="297" height="498"/>
	<SubTexture name="dancing-cat-dance_gif0153" x="3593" y="1505" width="297" height="498"/>
	<SubTexture name="dancing-cat-dance_gif0154" x="3593" y="1505" width="297" height="498"/>
	<SubTexture name="dancing-cat-dance_gif0155" x="3593" y="1505" width="297" height="498"/>
	<SubTexture name="dancing-cat-dance_gif0156" x="5" y="2005" width="297" height="498"/>
	<SubTexture name="dancing-cat-dance_gif0157" x="5" y="2005" width="297" height="498"/>
	<SubTexture name="dancing-cat-dance_gif0158" x="5" y="2005" width="297" height="498"/>
	<SubTexture name="dancing-cat-dance_gif0159" x="304" y="2005" width="297" height="498"/>
	<SubTexture name="dancing-cat-dance_gif0160" x="304" y="2005" width="297" height="498"/>
	<SubTexture name="dancing-cat-dance_gif0161" x="304" y="2005" width="297" height="498"/>
	<SubTexture name="dancing-cat-dance_gif0162" x="603" y="2005" width="297" height="498"/>
	<SubTexture name="dancing-cat-dance_gif0163" x="603" y="2005" width="297" height="498"/>
	<SubTexture name="dancing-cat-dance_gif0164" x="603" y="2005" width="297" height="498"/>
	<SubTexture name="dancing-cat-dance_gif0165" x="902" y="2005" width="297" height="498"/>
	<SubTexture name="dancing-cat-dance_gif0166" x="902" y="2005" width="297" height="498"/>
	<SubTexture name="dancing-cat-dance_gif0167" x="902" y="2005" width="297" height="498"/>
	<SubTexture name="dancing-cat-dance_gif0168" x="1201" y="2005" width="297" height="498"/>
	<SubTexture name="dancing-cat-dance_gif0169" x="1201" y="2005" width="297" height="498"/>
	<SubTexture name="dancing-cat-dance_gif0170" x="1201" y="2005" width="297" height="498"/>
	<SubTexture name="dancing-cat-dance_gif0171" x="1500" y="2005" width="297" height="498"/>
	<SubTexture name="dancing-cat-dance_gif0172" x="1500" y="2005" width="297" height="498"/>
	<SubTexture name="dancing-cat-dance_gif0173" x="1500" y="2005" width="297" height="498"/>
	<SubTexture name="dancing-cat-dance_gif0174" x="1799" y="2005" width="297" height="498"/>
	<SubTexture name="dancing-cat-dance_gif0175" x="1799" y="2005" width="297" height="498"/>
	<SubTexture name="dancing-cat-dance_gif0176" x="1799" y="2005" width="297" height="498"/>
</TextureAtlas>
