<?xml version="1.0" encoding="utf-8"?>
<TextureAtlas imagePath="bf_catches_gf.png">
	<!-- Created with Adobe Animate version 24.0.9.74 -->
	<!-- http://www.adobe.com/products/animate.html -->
	<SubTexture name="BF catches GF0000" x="5" y="5" width="579" height="507" frameX="-40" frameY="-96" frameWidth="634" frameHeight="603"/>
	<SubTexture name="BF catches GF0001" x="586" y="5" width="594" height="504" frameX="-40" frameY="-99" frameWidth="634" frameHeight="603"/>
	<SubTexture name="BF catches GF0002" x="1182" y="5" width="588" height="462" frameX="-30" frameY="-96" frameWidth="634" frameHeight="603"/>
	<SubTexture name="BF catches GF0003" x="1182" y="5" width="588" height="462" frameX="-30" frameY="-96" frameWidth="634" frameHeight="603"/>
	<SubTexture name="BF catches GF0004" x="1772" y="5" width="583" height="464" frameX="-30" frameY="-98" frameWidth="634" frameHeight="603"/>
	<SubTexture name="BF catches GF0005" x="2357" y="5" width="580" height="462" frameX="-30" frameY="-100" frameWidth="634" frameHeight="603"/>
	<SubTexture name="BF catches GF0006" x="2939" y="5" width="578" height="461" frameX="-30" frameY="-101" frameWidth="634" frameHeight="603"/>
	<SubTexture name="BF catches GF0007" x="2939" y="5" width="578" height="461" frameX="-30" frameY="-101" frameWidth="634" frameHeight="603"/>
	<SubTexture name="BF catches GF0008" x="5" y="514" width="578" height="461" frameX="-30" frameY="-101" frameWidth="634" frameHeight="603"/>
	<SubTexture name="BF catches GF0009" x="5" y="514" width="578" height="461" frameX="-30" frameY="-101" frameWidth="634" frameHeight="603"/>
	<SubTexture name="BF catches GF0010" x="5" y="514" width="578" height="461" frameX="-30" frameY="-101" frameWidth="634" frameHeight="603"/>
	<SubTexture name="BF catches GF0011" x="5" y="514" width="578" height="461" frameX="-30" frameY="-101" frameWidth="634" frameHeight="603"/>
	<SubTexture name="BF catches GF0012" x="585" y="514" width="529" height="483" frameX="-1" frameY="-39" frameWidth="634" frameHeight="603"/>
	<SubTexture name="BF catches GF0013" x="1116" y="514" width="529" height="509" frameX="-1" frameY="-13" frameWidth="634" frameHeight="603"/>
	<SubTexture name="BF catches GF0014" x="1647" y="514" width="523" height="509" frameX="0" frameY="-13" frameWidth="634" frameHeight="603"/>
	<SubTexture name="BF catches GF0015" x="2172" y="514" width="523" height="516" frameX="0" frameY="-6" frameWidth="634" frameHeight="603"/>
	<SubTexture name="BF catches GF0016" x="2697" y="514" width="525" height="516" frameX="0" frameY="-6" frameWidth="634" frameHeight="603"/>
	<SubTexture name="BF catches GF0017" x="3224" y="514" width="525" height="518" frameX="0" frameY="-4" frameWidth="634" frameHeight="603"/>
	<SubTexture name="BF catches GF0018" x="5" y="1034" width="526" height="518" frameX="0" frameY="-4" frameWidth="634" frameHeight="603"/>
	<SubTexture name="BF catches GF0019" x="533" y="1034" width="526" height="522" frameX="0" frameY="0" frameWidth="634" frameHeight="603"/>
	<SubTexture name="BF catches GF0020" x="533" y="1034" width="526" height="522" frameX="0" frameY="0" frameWidth="634" frameHeight="603"/>
	<SubTexture name="BF catches GF0021" x="1061" y="1034" width="526" height="521" frameX="0" frameY="-1" frameWidth="634" frameHeight="603"/>
	<SubTexture name="BF catches GF0022" x="1061" y="1034" width="526" height="521" frameX="0" frameY="-1" frameWidth="634" frameHeight="603"/>
	<SubTexture name="BF catches GF0023" x="1589" y="1034" width="526" height="520" frameX="0" frameY="-2" frameWidth="634" frameHeight="603"/>
</TextureAtlas>
